AFL/automation/__init__.py
AFL/automation/_version.py
AFL/automation/APIServer/APIServer.py
AFL/automation/APIServer/CAStatusPublisher.py
AFL/automation/APIServer/Client.py
AFL/automation/APIServer/Driver.py
AFL/automation/APIServer/DummyDriver.py
AFL/automation/APIServer/DummyOT2Driver.py
AFL/automation/APIServer/LoggerFilter.py
AFL/automation/APIServer/QueueDaemon.py
AFL/automation/APIServer/__init__.py
AFL/automation/APIServer/jupyterlite/README.md
AFL/automation/APIServer/jupyterlite/jupyter_lite_config.json
AFL/automation/APIServer/jupyterlite/requirements.txt
AFL/automation/APIServer/jupyterlite/files/BrowseDataset.ipynb
AFL/automation/APIServer/static/config-retro.html
AFL/automation/APIServer/static/config.html
AFL/automation/APIServer/static/logo.svg
AFL/automation/APIServer/static/ncnr.png
AFL/automation/APIServer/static/scripts.js
AFL/automation/APIServer/static/status.html
AFL/automation/APIServer/static/style.css
AFL/automation/APIServer/static/jl/bootstrap.js
AFL/automation/APIServer/static/jl/config-utils.js
AFL/automation/APIServer/static/jl/icon-120x120.png
AFL/automation/APIServer/static/jl/icon-512x512.png
AFL/automation/APIServer/static/jl/index.html
AFL/automation/APIServer/static/jl/jupyter-lite.ipynb
AFL/automation/APIServer/static/jl/jupyter-lite.json
AFL/automation/APIServer/static/jl/jupyterlite.schema.v0.json
AFL/automation/APIServer/static/jl/manifest.webmanifest
AFL/automation/APIServer/static/jl/package.json
AFL/automation/APIServer/static/jl/service-worker.js
AFL/automation/APIServer/static/jl/api/contents/all.json
AFL/automation/APIServer/static/jl/api/translations/all.json
AFL/automation/APIServer/static/jl/api/translations/en.json
AFL/automation/APIServer/static/jl/build/1053.75981ec.js
AFL/automation/APIServer/static/jl/build/1053.75981ec.js.map
AFL/automation/APIServer/static/jl/build/1088.33c6076.js
AFL/automation/APIServer/static/jl/build/1088.33c6076.js.map
AFL/automation/APIServer/static/jl/build/1091.1cf35e6.js
afl_automation-1.1.0.dist-info/METADATA
afl_automation-1.1.0.dist-info/WHEEL
afl_automation-1.1.0.dist-info/entry_points.txt
afl_automation-1.1.0.dist-info/licenses/LICENSE
afl_automation-1.1.0.dist-info/RECORD
